dp_wizard_templates/VERSION
dp_wizard_templates/__init__.py
dp_wizard_templates/code_template.py
dp_wizard_templates/converters.py
dp_wizard_templates/py.typed
dp_wizard_templates/ui.js
dp_wizard_templates-0.8.2.dist-info/licenses/LICENSE
dp_wizard_templates-0.8.2.dist-info/WHEEL
dp_wizard_templates-0.8.2.dist-info/METADATA
dp_wizard_templates-0.8.2.dist-info/RECORD
