Metadata-Version: 2.4
Name: dp_wizard_templates
Version: 0.8.2
Summary: .. include:: ../examples/tutorial.md
Author-email: The OpenDP Project <info@opendp.org>
License-File: LICENSE
Requires-Dist: black
Requires-Dist: ipykernel
Requires-Dist: jupyter-client
Requires-Dist: jupytext
Requires-Dist: nbconvert
Project-URL: GitHub, https://github.com/opendp/dp-wizard-templates
Project-URL: Homepage, https://opendp.github.io/dp-wizard-templates
